spark8t/__init__.py
spark8t/cli/__init__.py
spark8t/cli/params.py
spark8t/cli/pyspark.py
spark8t/cli/service_account_registry.py
spark8t/cli/spark_shell.py
spark8t/cli/spark_sql.py
spark8t/cli/spark_submit.py
spark8t/domain.py
spark8t/exceptions.py
spark8t/kube_interface/__init__.py
spark8t/kube_interface/base.py
spark8t/kube_interface/kubectl.py
spark8t/kube_interface/lightkube.py
spark8t/literals.py
spark8t/py.typed
spark8t/registry/__init__.py
spark8t/registry/base.py
spark8t/registry/k8s.py
spark8t/registry/memory.py
spark8t/resources/logging.yaml
spark8t/resources/templates/role_yaml.tmpl
spark8t/resources/templates/rolebinding_yaml.tmpl
spark8t/resources/templates/serviceaccount_yaml.tmpl
spark8t/session.py
spark8t/spark_interface.py
spark8t/utils.py
spark8t-1.2.0.dist-info/METADATA
spark8t-1.2.0.dist-info/WHEEL
spark8t-1.2.0.dist-info/licenses/LICENSE
spark8t-1.2.0.dist-info/RECORD
