Metadata-Version: 2.4
Name: spark8t
Version: 1.2.0
Summary: This project provides some utilities function and CLI commands to run Spark on K8s.
License: Apache-2.0
License-File: LICENSE
Author: Canonical Data Platform
Author-email: data-platform@lists.launchpad.net
Requires-Python: >=3.10,<4.0
Classifier: License :: OSI Approved :: Apache Software License
Classifier: Programming Language :: Python :: 3
Classifier: Programming Language :: Python :: 3.10
Classifier: Programming Language :: Python :: 3.11
Classifier: Programming Language :: Python :: 3.12
Classifier: Programming Language :: Python :: 3.13
Classifier: Programming Language :: Python :: 3.14
Requires-Dist: envyaml (>=1.10.211231)
Requires-Dist: jinja2 (>=3.1.6)
Requires-Dist: lightkube (>=0.18.0)
Requires-Dist: typing-extensions (>=4.15.0,<5.0.0)
